pervpy/__init__.py
pervpy/django_orm_watch.py
pervpy-0.1.3.dist-info/WHEEL
pervpy-0.1.3.dist-info/entry_points.txt
pervpy-0.1.3.dist-info/METADATA
pervpy-0.1.3.dist-info/RECORD
