Metadata-Version: 2.3
Name: pervpy
Version: 0.1.3
Summary: Analyzing and profiling python applications, innocently
Author: Vieolo B.V.
Requires-Python: >=3.11
